polymorphic_tree/__init__.py
polymorphic_tree/managers.py
polymorphic_tree/models.py
polymorphic_tree/admin/__init__.py
polymorphic_tree/admin/childadmin.py
polymorphic_tree/admin/parentadmin.py
polymorphic_tree/locale/nl/LC_MESSAGES/django.mo
polymorphic_tree/locale/nl/LC_MESSAGES/django.po
polymorphic_tree/static/polymorphic_tree/jquery.cookie.js
polymorphic_tree/static/polymorphic_tree/adminlist/arrow-down.gif
polymorphic_tree/static/polymorphic_tree/adminlist/arrow-up.gif
polymorphic_tree/static/polymorphic_tree/adminlist/nav-bg.gif
polymorphic_tree/static/polymorphic_tree/adminlist/nodetree.css
polymorphic_tree/static/polymorphic_tree/adminlist/nodetree_classic.css
polymorphic_tree/static/polymorphic_tree/adminlist/nodetree_flat.css
polymorphic_tree/static/polymorphic_tree/adminlist/nodetree_grapelli.css
polymorphic_tree/static/polymorphic_tree/adminlist/zebra-flat.png
polymorphic_tree/static/polymorphic_tree/adminlist/zebra-grapelli.png
polymorphic_tree/static/polymorphic_tree/adminlist/zebra.png
polymorphic_tree/static/polymorphic_tree/icons/blank.gif
polymorphic_tree/static/polymorphic_tree/icons/page_new.gif
polymorphic_tree/static/polymorphic_tree/icons/world.gif
polymorphic_tree/templates/admin/polymorphic_tree/change_form.html
polymorphic_tree/templates/admin/polymorphic_tree/change_form_breadcrumbs.html
polymorphic_tree/templates/admin/polymorphic_tree/change_list.html
polymorphic_tree/templates/admin/polymorphic_tree/delete_confirmation.html
polymorphic_tree/templates/admin/polymorphic_tree/jstree_list_results.html
polymorphic_tree/templates/admin/polymorphic_tree/object_history.html
polymorphic_tree/templates/admin/polymorphic_tree/object_history_breadcrumbs.html
polymorphic_tree/templates/admin/polymorphic_tree/stylable_change_list.html
polymorphic_tree/templatetags/__init__.py
polymorphic_tree/templatetags/polymorphic_tree_admin_tags.py
polymorphic_tree/templatetags/stylable_admin_list.py
sigmacms_polymorphic_tree-1.2.6b1.dist-info/DESCRIPTION.rst
sigmacms_polymorphic_tree-1.2.6b1.dist-info/METADATA
sigmacms_polymorphic_tree-1.2.6b1.dist-info/RECORD
sigmacms_polymorphic_tree-1.2.6b1.dist-info/WHEEL
sigmacms_polymorphic_tree-1.2.6b1.dist-info/metadata.json
sigmacms_polymorphic_tree-1.2.6b1.dist-info/top_level.txt
