Metadata-Version: 2.0
Name: sigmacms-polymorphic-tree
Version: 1.2.6b1
Summary: A polymorphic mptt structure to display content in a tree.
Home-page: https://github.com/sigmacms/sigmacms-polymorphic-tree
Author: Diederik van der Boor
Author-email: opensource@edoburu.nl
License: Apache 2.0
Download-URL: https://github.com/sigmacms/sigmacms-polymorphic-tree/zipball/master
Platform: UNKNOWN
Classifier: Development Status :: 5 - Production/Stable
Classifier: Environment :: Web Environment
Classifier: Framework :: Django
Classifier: Intended Audience :: Developers
Classifier: License :: OSI Approved :: Apache Software License
Classifier: Operating System :: OS Independent
Classifier: Programming Language :: Python
Classifier: Programming Language :: Python :: 2.6
Classifier: Programming Language :: Python :: 2.7
Classifier: Programming Language :: Python :: 3.3
Classifier: Framework :: Django
Classifier: Framework :: Django :: 1.4
Classifier: Framework :: Django :: 1.5
Classifier: Framework :: Django :: 1.6
Classifier: Framework :: Django :: 1.7
Classifier: Framework :: Django :: 1.8
Classifier: Topic :: Internet :: WWW/HTTP
Classifier: Topic :: Internet :: WWW/HTTP :: Dynamic Content
Classifier: Topic :: Software Development :: Libraries :: Python Modules
Requires: Django (>=1.5)
Requires-Dist: django-mptt (>=0.6.0)
Requires-Dist: django-polymorphic (>=0.9.1)
Requires-Dist: django-tag-parser (>=2.1)
Requires-Dist: future (>=0.12.2)
